MANIFEST.in
Pipfile
Pipfile.lock
README.md
setup.py
django_kelove_db/__init__.py
django_kelove_db/admin.py
django_kelove_db/apps.py
django_kelove_db/fields.py
django_kelove_db/forms.py
django_kelove_db/helper.py
django_kelove_db/models.py
django_kelove_db/urls.py
django_kelove_db/views.py
django_kelove_db/widgets.py
django_kelove_db.egg-info/PKG-INFO
django_kelove_db.egg-info/SOURCES.txt
django_kelove_db.egg-info/dependency_links.txt
django_kelove_db.egg-info/requires.txt
django_kelove_db.egg-info/top_level.txt
django_kelove_db/backends/__init__.py
django_kelove_db/backends/base/__init__.py
django_kelove_db/backends/base/doc.py
django_kelove_db/backends/mysql/__init__.py
django_kelove_db/backends/mysql/base.py
django_kelove_db/backends/mysql/doc.py
django_kelove_db/backends/mysql/schema.py
django_kelove_db/static/django_kelove_db/bootstrap4/css/bootstrap.min.css
django_kelove_db/static/django_kelove_db/bootstrap4/js/bootstrap.bundle.min.js
django_kelove_db/static/django_kelove_db/doc/css/editormd.min.css
django_kelove_db/static/django_kelove_db/doc/css/style.css
django_kelove_db/static/django_kelove_db/doc/css/theme.css
django_kelove_db/static/django_kelove_db/doc/fonts/icons.eot
django_kelove_db/static/django_kelove_db/doc/fonts/icons.svg
django_kelove_db/static/django_kelove_db/doc/fonts/icons.ttf
django_kelove_db/static/django_kelove_db/doc/fonts/icons.woff
django_kelove_db/static/django_kelove_db/doc/fonts/icons.woff2
django_kelove_db/static/django_kelove_db/doc/images/loading.gif
django_kelove_db/static/django_kelove_db/doc/js/editormd.min.js
django_kelove_db/static/django_kelove_db/doc/js/marked.min.js
django_kelove_db/static/django_kelove_db/doc/js/prettify.min.js
django_kelove_db/static/django_kelove_db/doc/js/script.js
django_kelove_db/static/django_kelove_db/editor_md/editormd.amd.min.js
django_kelove_db/static/django_kelove_db/editor_md/editormd.min.js
django_kelove_db/static/django_kelove_db/editor_md/css/editormd.logo.min.css
django_kelove_db/static/django_kelove_db/editor_md/css/editormd.min.css
django_kelove_db/static/django_kelove_db/editor_md/css/editormd.preview.min.css
django_kelove_db/static/django_kelove_db/editor_md/fonts/FontAwesome.otf
