Metadata-Version: 2.1
Name: django-kelove-db
Version: 3.1.0
Summary: Django Db 增强（目前只完善MySQL）
Home-page: https://e.coding.net/xqitw/django-kelove/django-kelove-db.git
Author: IT小强xqitw.cn
Author-email: mail@xqitw.cn
License: Apache-2.0
Keywords: django,mysql,comment
Platform: UNKNOWN
Classifier: Intended Audience :: Developers
Classifier: Natural Language :: Chinese (Simplified)
Classifier: Programming Language :: Python
Classifier: Programming Language :: Python :: 3
Classifier: Programming Language :: Python :: 3.7
Classifier: Programming Language :: Python :: 3.8
Requires-Python: >=3.7.0
